pyburner/__init__.py
pyburner/client.py
pyburner/websocket.py
pyBurner-1.0.2.dist-info/LICENSE
pyBurner-1.0.2.dist-info/METADATA
pyBurner-1.0.2.dist-info/WHEEL
pyBurner-1.0.2.dist-info/top_level.txt
pyBurner-1.0.2.dist-info/RECORD
